[
  {
    "ayah": 1,
    "arabic": "وَيْلٌۭ لِّكُلِّ هُمَزَةٍۢ لُّمَزَةٍ",
    "transliteration": "Veylun li kulli humezetin lumezeh",
    "audio": "https://everyayah.com/data/Alafasy_128kbps/104001.mp3",
    "translations": {
      "tr": "Mal toplayarak onu tekrar tekrar sayan, diliyle çekiştirip alay eden kimsenin vay haline!",
      "en": "Woe to every scorner and mocker",
      "de": "Wehe jedem Stichler und Nörgler,",
      "fr": "Malheur à tout calomniateur diffamateur,",
      "id": "Kecelakaanlah bagi setiap pengumpat lagi pencela,",
      "ur": "ہر طعن آمیز اشارتیں کرنے والے چغل خور کی خرابی ہے",
      "bn": "প্রত্যেক পশ্চাতে ও সম্মুখে পরনিন্দাকারীর দুর্ভোগ,",
      "fa": "وای بر هر عیبجوی مسخره‌کننده‌ای!",
      "ru": "Горе всякому хулителю и обидчику,"
    }
  },
  {
    "ayah": 2,
    "arabic": "ٱلَّذِى جَمَعَ مَالًۭا وَعَدَّدَهُۥ",
    "transliteration": "Ellezi cemea malen ve addedeh",
    "audio": "https://everyayah.com/data/Alafasy_128kbps/104002.mp3",
    "translations": {
      "tr": "Mal toplayarak onu tekrar tekrar sayan, diliyle çekiştirip alay eden kimsenin vay haline!",
      "en": "Who collects wealth and [continuously] counts it.",
      "de": "der Besitz zusammenträgt und ihn zählt und immer wieder zählt,",
      "fr": "qui amasse une fortune et la compte,",
      "id": "yang mengumpulkan harta dan menghitung-hitung,",
      "ur": "جو مال جمع کرتا اور اس کو گن گن کر رکھتا ہے",
      "bn": "যে অর্থ সঞ্চিত করে ও গণনা করে",
      "fa": "همان کس که مال فراوانی جمع‌آوری و شماره کرده (بی‌آنکه مشروع و نامشروع آن را حساب کند)!",
      "ru": "который копит состояние и пересчитывает его,"
    }
  },
  {
    "ayah": 3,
    "arabic": "يَحْسَبُ أَنَّ مَالَهُۥٓ أَخْلَدَهُۥ",
    "transliteration": "Yahsebu enne malehu ahledeh",
    "audio": "https://everyayah.com/data/Alafasy_128kbps/104003.mp3",
    "translations": {
      "tr": "Malının kendisini ölümsüz kılacağını sanır.",
      "en": "He thinks that his wealth will make him immortal.",
      "de": "wobei er meint, daß sein Besitz ihn ewig leben ließe!",
      "fr": "pensant que sa fortune l'immortalisera.",
      "id": "dia mengira bahwa hartanya itu dapat mengkekalkannya,",
      "ur": "(اور) خیال کرتا ہے کہ اس کا مال اس کی ہمیشہ کی زندگی کا موجب ہو گا",
      "bn": "সে মনে করে যে, তার অর্থ চিরকাল তার সাথে থাকবে!",
      "fa": "او گمان می‌کند که اموالش او را جاودانه می‌سازد!",
      "ru": "думая, что богатство увековечит его."
    }
  },
  {
    "ayah": 4,
    "arabic": "كَلَّا ۖ لَيُنۢبَذَنَّ فِى ٱلْحُطَمَةِ",
    "transliteration": "Kella le yunbezenne fil hutameh",
    "audio": "https://everyayah.com/data/Alafasy_128kbps/104004.mp3",
    "translations": {
      "tr": "Hayır; o, and olsun ki, Hutame'ye atılacaktır.",
      "en": "No! He will surely be thrown into the Crusher.",
      "de": "Keineswegs! Er wird ganz gewiß in al-Hutama geworfen werden.",
      "fr": "Mais non! Il sera certes, jeté dans la Hutamah.",
      "id": "sekali-kali tidak! Sesungguhnya dia benar-benar akan dilemparkan ke dalam Huthamah.",
      "ur": "ہر گز نہیں وہ ضرور حطمہ میں ڈالا جائے گا",
      "bn": "কখনও না, সে অবশ্যই নিক্ষিপ্ত হবে পিষ্টকারীর মধ্যে।",
      "fa": "چنین نیست که می‌پندارد؛ بزودی در «حُطَمه» [= آتشی خردکننده‌] پرتاب می‌شود!",
      "ru": "Но нет! Его непременно ввергнут в Огонь сокрушающий."
    }
  },
  {
    "ayah": 5,
    "arabic": "وَمَآ أَدْرَىٰكَ مَا ٱلْحُطَمَةُ",
    "transliteration": "Ve ma edrake mel hutameh",
    "audio": "https://everyayah.com/data/Alafasy_128kbps/104005.mp3",
    "translations": {
      "tr": "Hutame'nin ne olduğunu sen bilir misin?",
      "en": "And what can make you know what is the Crusher?",
      "de": "Was läßt dich wissen, was al-Hutama ist?",
      "fr": "Et qui te dira ce qu'est la Hutamah?",
      "id": "Dan tahukah kamu apa Huthamah itu?",
      "ur": "اور تم کیا سمجھے حطمہ کیا ہے؟",
      "bn": "আপনি কি জানেন, পিষ্টকারী কি?",
      "fa": "و تو چه می‌دانی «حُطمه» چیست؟!",
      "ru": "Откуда ты мог знать, что такое Огонь сокрушающий?"
    }
  },
  {
    "ayah": 6,
    "arabic": "نَارُ ٱللَّهِ ٱلْمُوقَدَةُ",
    "transliteration": "Narullahil mukadeh",
    "audio": "https://everyayah.com/data/Alafasy_128kbps/104006.mp3",
    "translations": {
      "tr": "O, yüreklere çökecek olan, Allah'ın tutuşturulmuş ateşidir.",
      "en": "It is the fire of Allah, [eternally] fueled,",
      "de": "(Sie ist) Allahs entfachtes Feuer,",
      "fr": "Le Feu attisé d'Allah",
      "id": "(yaitu) api (yang disediakan) Allah yang dinyalakan,",
      "ur": "وہ خدا کی بھڑکائی ہوئی آگ ہے",
      "bn": "এটা আল্লাহর প্রজ্জ্বলিত অগ্নি,",
      "fa": "آتش برافروخته الهی است،",
      "ru": "Это - разожженный Огонь Аллаха,"
    }
  },
  {
    "ayah": 7,
    "arabic": "ٱلَّتِى تَطَّلِعُ عَلَى ٱلْأَفْـِٔدَةِ",
    "transliteration": "Elleti tettaliu alel ef'ideh",
    "audio": "https://everyayah.com/data/Alafasy_128kbps/104007.mp3",
    "translations": {
      "tr": "O, yüreklere çökecek olan, Allah'ın tutuşturulmuş ateşidir.",
      "en": "Which mounts directed at the hearts.",
      "de": "das Einblick in die Herzen gewinnt.",
      "fr": "qui monte jusqu'aux cœurs.",
      "id": "yang (membakar) sampai ke hati.",
      "ur": "جو دلوں پر جا لپٹے گی",
      "bn": "যা হৃদয় পর্যন্ত পৌছবে।",
      "fa": "آتشی که از دلها سرمی‌زند!",
      "ru": "который вздымается над сердцами."
    }
  },
  {
    "ayah": 8,
    "arabic": "إِنَّهَا عَلَيْهِم مُّؤْصَدَةٌۭ",
    "transliteration": "İnneha aleyhim mu'sadeh",
    "audio": "https://everyayah.com/data/Alafasy_128kbps/104008.mp3",
    "translations": {
      "tr": "Onlar, uzun sütunlar arasında, her yönden o ateşle kapatılmışlardır.",
      "en": "Indeed, Hellfire will be closed down upon them",
      "de": "Gewiß, es wird sie einschließen",
      "fr": "Il se refermera sur eux,",
      "id": "Sesungguhnya api itu ditutup rapat atas mereka,",
      "ur": "(اور) وہ اس میں بند کر دیئے جائیں گے",
      "bn": "এতে তাদেরকে বেঁধে দেয়া হবে,",
      "fa": "این آتش بر آنها فروبسته شده،",
      "ru": "Воистину, он сомкнется над ними"
    }
  },
  {
    "ayah": 9,
    "arabic": "فِى عَمَدٍۢ مُّمَدَّدَةٍۭ",
    "transliteration": "Fi amedin mumeddedeh",
    "audio": "https://everyayah.com/data/Alafasy_128kbps/104009.mp3",
    "translations": {
      "tr": "Onlar, uzun sütunlar arasında, her yönden o ateşle kapatılmışlardır.",
      "en": "In extended columns.",
      "de": "in langgestreckten Säulen.",
      "fr": "en colonnes (de flammes) étendues.",
      "id": "(sedang mereka itu) diikat pada tiang-tiang yang panjang.",
      "ur": "(یعنی آگ کے) لمبے لمبے ستونوں میں",
      "bn": "লম্বা লম্বা খুঁটিতে।",
      "fa": "در ستونهای کشیده و طولانی!",
      "ru": "высокими столбами (мученики будут прикованы к этим столбам или врата Ада будут заперты и закреплены этими столбами)."
    }
  }
]
